aws_cloud_utilities/__init__.py
aws_cloud_utilities/cli.py
aws_cloud_utilities/commands/__init__.py
aws_cloud_utilities/commands/account.py
aws_cloud_utilities/commands/awsconfig.py
aws_cloud_utilities/commands/bedrock.py
aws_cloud_utilities/commands/billing.py
aws_cloud_utilities/commands/cloudformation.py
aws_cloud_utilities/commands/cloudfront.py
aws_cloud_utilities/commands/costops.py
aws_cloud_utilities/commands/ecr.py
aws_cloud_utilities/commands/iam.py
aws_cloud_utilities/commands/inventory.py
aws_cloud_utilities/commands/logs.py
aws_cloud_utilities/commands/networking.py
aws_cloud_utilities/commands/rds.py
aws_cloud_utilities/commands/s3.py
aws_cloud_utilities/commands/security.py
aws_cloud_utilities/commands/stepfunctions.py
aws_cloud_utilities/commands/support.py
aws_cloud_utilities/commands/waf.py
aws_cloud_utilities/core/__init__.py
aws_cloud_utilities/core/auth.py
aws_cloud_utilities/core/config.py
aws_cloud_utilities/core/exceptions.py
aws_cloud_utilities/core/utils.py
aws_cloud_utilities/models/__init__.py
aws_cloud_utilities/models/aws_resources.py
aws_cloud_utilities-2.1.2.dist-info/METADATA
aws_cloud_utilities-2.1.2.dist-info/WHEEL
aws_cloud_utilities-2.1.2.dist-info/entry_points.txt
aws_cloud_utilities-2.1.2.dist-info/top_level.txt
aws_cloud_utilities-2.1.2.dist-info/RECORD
