Metadata-Version: 2.4
Name: aws-cloud-utilities
Version: 2.1.2
Summary: A unified command-line toolkit for AWS operations with enhanced functionality
Author-email: Jon <jon@zer0day.net>
Maintainer-email: Jon <jon@zer0day.net>
License: MIT
Project-URL: Homepage, https://github.com/jon-the-dev/aws-cloud-tools
Project-URL: Repository, https://github.com/jon-the-dev/aws-cloud-tools
Project-URL: Issues, https://github.com/jon-the-dev/aws-cloud-tools/issues
Project-URL: Documentation, https://github.com/jon-the-dev/aws-cloud-tools/tree/main/docs
Keywords: aws,cloud,cli,utilities,devops
Classifier: Development Status :: 4 - Beta
Classifier: Intended Audience :: Developers
Classifier: Intended Audience :: System Administrators
Classifier: License :: OSI Approved :: MIT License
Classifier: Operating System :: OS Independent
Classifier: Programming Language :: Python :: 3
Classifier: Programming Language :: Python :: 3.12
Classifier: Topic :: System :: Systems Administration
Classifier: Topic :: Utilities
Requires-Python: >=3.12
Requires-Dist: boto3>=1.34.0
Requires-Dist: click>=8.0.0
Requires-Dist: python-dotenv>=1.0.0
Requires-Dist: pydantic>=2.0.0
Requires-Dist: PyYAML>=6.0.0
Requires-Dist: rich>=13.0.0
Requires-Dist: tabulate>=0.9.0
Requires-Dist: requests>=2.31.0
Requires-Dist: pandas>=2.0.0
Provides-Extra: dev
Requires-Dist: pytest>=7.0.0; extra == "dev"
Requires-Dist: pytest-cov>=4.0.0; extra == "dev"
Requires-Dist: black>=23.0.0; extra == "dev"
Requires-Dist: flake8>=6.0.0; extra == "dev"
Requires-Dist: mypy>=1.0.0; extra == "dev"
Requires-Dist: pre-commit>=3.0.0; extra == "dev"
Provides-Extra: docs
Requires-Dist: mkdocs>=1.5.0; extra == "docs"
Requires-Dist: mkdocs-material>=9.0.0; extra == "docs"
Requires-Dist: mkdocstrings[python]>=0.20.0; extra == "docs"
